alphavantage_mcp_server/__init__.py
alphavantage_mcp_server/api.py
alphavantage_mcp_server/server.py
alphavantage_mcp_server-0.1.3.dist-info/licenses/LICENSE
alphavantage_mcp_server-0.1.3.dist-info/METADATA
alphavantage_mcp_server-0.1.3.dist-info/WHEEL
alphavantage_mcp_server-0.1.3.dist-info/entry_points.txt
alphavantage_mcp_server-0.1.3.dist-info/top_level.txt
alphavantage_mcp_server-0.1.3.dist-info/RECORD
