Metadata-Version: 2.4
Name: alphavantage-mcp-server
Version: 0.1.3
Summary: Alphavantage MCP server
Requires-Python: >=3.13
License-File: LICENSE
Requires-Dist: asyncio>=3.4.3
Requires-Dist: bump2version>=1.0.1
Requires-Dist: load-dotenv>=0.1.0
Requires-Dist: mcp>=1.6.0
Requires-Dist: toml>=0.10.2
Dynamic: license-file
